[
    {
        "q": "What will happen if in a C program you assign a value to an array element whose subscript exceeds the size of array?", 
        "options": [
            "The element will be set to 0.", 
            "The compiler would report an error.", 
            "The program may crash if some important data gets overwritten.", 
            "The array size would appropriately grow."
        ], 
        "ans": "C"
    }, 
    {
        "q": "What does the following declaration mean?\nint (*ptr)[10];", 
        "options": [
            "ptr is array of pointers to 10 integers", 
            "ptr is a pointer to an array of 10 integers", 
            "ptr is an array of 10 integers", 
            "ptr is an pointer to array"
        ], 
        "ans": "B"
    }, 
    {
        "q": "In C, if you pass an array as an argument to a function, what actually gets passed?", 
        "options": [
            "Value of elements in array", 
            "First element of the array", 
            "Base address of the array", 
            "Address of the last element of array"
        ], 
        "ans": "C"
    }
]